arraydeque.pypy311-pp73-win_amd64.pyd
arraydeque-1.4.0.dist-info/licenses/LICENSE
arraydeque-1.4.0.dist-info/METADATA
arraydeque-1.4.0.dist-info/WHEEL
arraydeque-1.4.0.dist-info/top_level.txt
arraydeque-1.4.0.dist-info/RECORD
